pyembed_mustache-1.1.0-py2.7-nspkg.pth
pyembed_mustache-1.1.0.dist-info/metadata.json
pyembed_mustache-1.1.0.dist-info/top_level.txt
pyembed_mustache-1.1.0.dist-info/METADATA
pyembed_mustache-1.1.0.dist-info/RECORD
pyembed_mustache-1.1.0.dist-info/WHEEL
pyembed_mustache-1.1.0.dist-info/DESCRIPTION.rst
pyembed_mustache-1.1.0.dist-info/namespace_packages.txt
pyembed/mustache/__init__.py
pyembed/mustache/templates/rich.mustache
pyembed/mustache/templates/link.mustache
pyembed/mustache/templates/video.mustache
pyembed/mustache/templates/photo.mustache
